[
  {
    "project_name": "ray",
    "project_version": "2.8.1",
    "project_release": "ray-2.8.1-cp39-cp39-macosx_10_15_x86_64.whl",
    "uploaded_on": "2023-12-01 03:27:43.971",
    "path": "packages/ray/ray-2.8.1-cp39-cp39-macosx_10_15_x86_64.whl/ray-2.8.1.data/purelib/ray/thirdparty_files/psutil-5.9.6.dist-info/top_level.txt",
    "archive_path": "ray-2.8.1.data/purelib/ray/thirdparty_files/psutil-5.9.6.dist-info/top_level.txt",
    "size": 7,
    "hash": "\\xA4\\xD9,\\xC0\\x8D\\xB6\\xA0\\xD8\\xBF\\xED\\xBB\\xBDb\\x0D\\x1F\\xB1\\x1F\\x84g{",
    "skip_reason": "",
    "lines": 1,
    "repository": 244
  },
  {
    "project_name": "tf-nightly-tpu",
    "project_version": "2.16.0.dev20231208",
    "project_release": "tf_nightly_tpu-2.16.0.dev20231208-cp311-cp311-manylinux_2_17_x86_64.manylinux2014_x86_64.whl",
    "uploaded_on": "2023-12-08 13:38:48.608",
    "path": "packages/tf-nightly-tpu/tf_nightly_tpu-2.16.0.dev20231208-cp311-cp311-manylinux_2_17_x86_64.manylinux2014_x86_64.whl/tensorflow/python/grappler/__init__.py",
    "archive_path": "tensorflow/python/grappler/__init__.py",
    "size": 0,
    "hash": "\\xE6\\x9D\\xE2\\x9B\\xB2\\xD1\\xD6CK\\x8B)\\xAEwZ\\xD8\\xC2\\xE4\\x8CS\\x91",
    "skip_reason": "empty",
    "lines": 0,
    "repository": 245
  }
]
