[
  {
    "project_name": "iprir",
    "project_version": "0.1.2.dev0",
    "project_release": "iprir-0.1.2.dev0-py3-none-any.whl",
    "uploaded_on": "2017-01-25 06:56:56.659",
    "path": "packages/iprir/iprir-0.1.2.dev0-py3-none-any.whl/iprir-0.1.2.dev0.dist-info/pbr.json",
    "archive_path": "iprir-0.1.2.dev0.dist-info/pbr.json",
    "size": 47,
    "hash": "\\xBAE\\x91\\xBC\\x13\\x16n\\xA0\\x06\\x96\\x9F\\xC1P\\xD7\\x84\\x11yx\\x98\\x0B",
    "skip_reason": "",
    "lines": 1,
    "repository": 19
  },
  {
    "project_name": "SCET",
    "project_version": "2.0.108",
    "project_release": "SCET-2.0.108.tar.gz",
    "uploaded_on": "2017-07-13 14:42:48.316",
    "path": "packages/SCET/SCET-2.0.108.tar.gz/SCET-2.0.108/scet/Recursos/editar-limpiar_64.png",
    "archive_path": "SCET-2.0.108/scet/Recursos/editar-limpiar_64.png",
    "size": 596,
    "hash": "]\\x8D\\xCA\\xFA\\xA3B\\x0B\\xCD4\\x16\\xA8u\\xBAU\\x85\\xADj\\xF8\\xA6.",
    "skip_reason": "binary",
    "lines": 0,
    "repository": 23
  }
]
